{
    "ticker": {
        "current_price": 168417,
        "delta_value": 3593,
        "delta_percent": 2.18,
        "direction": "up",
        "volume": 22,
        "volatility": 13851
    },
    "charts": {
        "history_dates": [
            "2026-01-11",
            "2026-01-12",
            "2026-01-13",
            "2026-01-16",
            "2026-01-17",
            "2026-01-18",
            "2026-01-19",
            "2026-01-20",
            "2026-01-21",
            "2026-01-22",
            "2026-01-23",
            "2026-01-24",
            "2026-01-25",
            "2026-01-26",
            "2026-01-27",
            "2026-01-28",
            "2026-01-29"
        ],
        "history_prices": [
            166147,
            166147,
            165857,
            166147,
            169719,
            169777,
            169748,
            165621,
            165000,
            164516,
            162591,
            162552,
            162552,
            162552,
            164824,
            164824,
            168417
        ],
        "history_sma_7": [
            0,
            0,
            0,
            0,
            0,
            0,
            167648,
            167573,
            167409,
            167218,
            166710,
            165686,
            164654,
            163626,
            163512,
            163487,
            164044
        ],
        "price_by_day_descanso": {
            "JUEVES IMPAR": 169040,
            "JUEVES PAR": 170495,
            "LUNES": 150000,
            "LUNES IMPAR": 187050,
            "LUNES PAR": 187252,
            "MARTES PAR": 174642,
            "MIERCOLES IMPAR": 175783,
            "NO ESPECIFICADO": 159077,
            "VIERNES IMPAR": 160161
        }
    },
    "market_depth": {
        "cheapest_offers": [
            {
                "fuente": "MILANUNCIOS",
                "dia": "NO ESPECIFICADO",
                "modelo": "DESCONOCIDO",
                "precio_neto": 135563,
                "precio_total": 140000,
                "valor_coche": 4437
            },
            {
                "fuente": "MILANUNCIOS",
                "dia": "LUNES",
                "modelo": "SIN COCHE",
                "precio_neto": 150000,
                "precio_total": 150000,
                "valor_coche": 0
            },
            {
                "fuente": "SOLANO",
                "dia": "VIERNES IMPAR",
                "modelo": "TOYOTA PRIUS",
                "precio_neto": 153264,
                "precio_total": 176000,
                "valor_coche": 22736
            },
            {
                "fuente": "STAC",
                "dia": "NO ESPECIFICADO",
                "modelo": "DESCONOCIDO",
                "precio_neto": 153563,
                "precio_total": 158000,
                "valor_coche": 4437
            },
            {
                "fuente": "STAC",
                "dia": "NO ESPECIFICADO",
                "modelo": "DESCONOCIDO",
                "precio_neto": 155563,
                "precio_total": 160000,
                "valor_coche": 4437
            }
        ],
        "all_offers": [
            {
                "fuente": "MILANUNCIOS",
                "precio_neto": 135563,
                "modelo": "DESCONOCIDO",
                "dia": "NO ESPECIFICADO",
                "raw": "Licencia Taxi Barcelona | 140.000 € | Barcelona (Barcelona) | Compro licencia de taxi en Barcelona c..."
            },
            {
                "fuente": "MILANUNCIOS",
                "precio_neto": 175000,
                "modelo": "SIN COCHE",
                "dia": "MARTES PAR",
                "raw": "Vendo licencia de taxi amb barcelona | 175.000 € | Barcelona (Barcelona) | Vendo licencia de taxi so..."
            },
            {
                "fuente": "MILANUNCIOS",
                "precio_neto": 150000,
                "modelo": "SIN COCHE",
                "dia": "LUNES",
                "raw": "Compro licencia de taxi en Barcelona | 150.000 € | Barcelona (Barcelona) | Compramos licencias de ta..."
            },
            {
                "fuente": "MILANUNCIOS",
                "precio_neto": 187050,
                "modelo": "TOYOTA COROLLA",
                "dia": "LUNES IMPAR",
                "raw": "6 | LUNES LICENCIA DE TAXI BARCELONA | 210.000 € | Barcelona (Barcelona) | NO NEGOCIABLE \nFiesta Lun..."
            },
            {
                "fuente": "MILANUNCIOS",
                "precio_neto": 187252,
                "modelo": "TOYOTA CAMRY",
                "dia": "LUNES PAR",
                "raw": "6 | LUNES LICENCIA DE TAXI BARCELONA | 205.000 € | L' Hospitalet de Llobregat (Barcelona) | NO NEGOC..."
            },
            {
                "fuente": "SOLANO",
                "precio_neto": 160250,
                "modelo": "DACIA JOGGER",
                "dia": "JUEVES IMPAR",
                "raw": "Ref:  | 38579 | DIA DE FIESTA:  | JUEVES PAR | LICENCIA DE TAXI EN VENTA BARCELONA | LICENCIA DE TAX..."
            },
            {
                "fuente": "SOLANO",
                "precio_neto": 174285,
                "modelo": "FORD CUSTOM",
                "dia": "MARTES PAR",
                "raw": "Ref:  | 38572 | DIA DE FIESTA:  | MARTES PAR | LICENCIA DE TAXI EN VENTA BARCELONA | LICENCIA DE TAX..."
            },
            {
                "fuente": "SOLANO",
                "precio_neto": 175783,
                "modelo": "DACIA",
                "dia": "MIERCOLES IMPAR",
                "raw": "Ref:  | 38574 | DIA DE FIESTA:  | MIERCOLES IMPAR | LICENCIA TAXI EN VENTA BARCELONA | LICENCIA TAXI..."
            },
            {
                "fuente": "SOLANO",
                "precio_neto": 159582,
                "modelo": "DACIA",
                "dia": "JUEVES IMPAR",
                "raw": "Ref:  | 38570 | DIA DE FIESTA:  | JUEVES IMPAR | LICENCIA DE TAXI EN VENTA BARCELONA | LICENCIA TAXI..."
            },
            {
                "fuente": "SOLANO",
                "precio_neto": 153264,
                "modelo": "TOYOTA PRIUS",
                "dia": "VIERNES IMPAR",
                "raw": "Ref:  | 38561 | DIA DE FIESTA:  | VIERNES IMPAR | JUBILACIÓN FINAL ABRIL 2026 | LICENCIA TAXI EN VEN..."
            },
            {
                "fuente": "SOLANO",
                "precio_neto": 178896,
                "modelo": "TOYOTA COROLLA",
                "dia": "JUEVES IMPAR",
                "raw": "Ref:  | 38553 | DIA DE FIESTA:  | JUEVES IMPAR | LICENCIA TAXI EN VENTA BARCELONA | LICENCIA TAXI EN..."
            },
            {
                "fuente": "SOLANO",
                "precio_neto": 169777,
                "modelo": "TOYOTA COROLLA",
                "dia": "JUEVES PAR",
                "raw": "Ref:  | 38538 | DIA DE FIESTA:  | JUEVES PAR | LICENCIA DE TAXI EN VENTA BARCELONA | LICENCIA TAXI E..."
            },
            {
                "fuente": "SOLANO",
                "precio_neto": 177830,
                "modelo": "VOLKSWAGEN CADDY",
                "dia": "JUEVES IMPAR",
                "raw": "Ref:  | 38525 | DIA DE FIESTA:  | JUEVES IMPAR | licencia taxi en venta barcelona | LICENCIA TAXI EN..."
            },
            {
                "fuente": "SOLANO",
                "precio_neto": 171213,
                "modelo": "DESCONOCIDO",
                "dia": "JUEVES PAR",
                "raw": "Ref:  | 38502 | DIA DE FIESTA:  | JUEVES PAR | LICENCIA TAXI EN VENTA BARCELONA | LICENCIA DE TAXI E..."
            },
            {
                "fuente": "SOLANO",
                "precio_neto": 167058,
                "modelo": "DACIA JOGGER",
                "dia": "VIERNES IMPAR",
                "raw": "Ref:  | 38500 | DIA DE FIESTA:  | VIERNES IMPAR | LICENCIA TAXI EN VENTA BARCELONA | LICENCIA TAXI E..."
            },
            {
                "fuente": "STAC",
                "precio_neto": 153563,
                "modelo": "DESCONOCIDO",
                "dia": "NO ESPECIFICADO",
                "raw": "Referencia: 932 |  | Se vende licencia sin vehículo. | Precio: 158000€ | + INFO..."
            },
            {
                "fuente": "STAC",
                "precio_neto": 163052,
                "modelo": "TOYOTA COROLLA",
                "dia": "NO ESPECIFICADO",
                "raw": "Referencia: 929 |  | Se vende licencia con vehículo TOYOTA COROLLA SEDAN con 3 años de antigüedad y ..."
            },
            {
                "fuente": "STAC",
                "precio_neto": 155563,
                "modelo": "DESCONOCIDO",
                "dia": "NO ESPECIFICADO",
                "raw": "Referencia: 923 |  | Se vende licencia sin vehículo. | Precio: 160000€ | + INFO..."
            },
            {
                "fuente": "STAC",
                "precio_neto": 155563,
                "modelo": "DESCONOCIDO",
                "dia": "NO ESPECIFICADO",
                "raw": "Referencia: 886 |  | Se vende licencia sin vehículo. | Precio: 160000€ | + INFO..."
            },
            {
                "fuente": "STAC",
                "precio_neto": 187570,
                "modelo": "MERCEDES VITO",
                "dia": "NO ESPECIFICADO",
                "raw": "Referencia: 870 |  | Se vende licencia con vehículo Mercedes Vito PMR 7PAX con 2 años de antigüedad ..."
            },
            {
                "fuente": "STAC",
                "precio_neto": 162591,
                "modelo": "DACIA JOGGER",
                "dia": "NO ESPECIFICADO",
                "raw": "Referencia: 847 |  | Se vende licencia con vehículo Dacia Jogger GLP Manual con 2 años de antigüedad..."
            },
            {
                "fuente": "STAC",
                "precio_neto": 183637,
                "modelo": "TESLA",
                "dia": "NO ESPECIFICADO",
                "raw": "Referencia: 734 |  | Se vende licencia con vehículo Tesla ELECTRICO con 1 años de antigüedad y 52000..."
            }
        ]
    },
    "updated_at": "29/01/2026 07:41"
}